LICENSE
MANIFEST.in
README.rst
setup.py
django_iprir.egg-info/PKG-INFO
django_iprir.egg-info/SOURCES.txt
django_iprir.egg-info/dependency_links.txt
django_iprir.egg-info/top_level.txt
iprir/__init__.py
iprir/admin.py
iprir/helpers.py
iprir/models.py
iprir/settings.py
iprir/tests.py
iprir/urls.py
iprir/utils.py
iprir/views.py
iprir/management/commands/loadregistry.py
iprir/management/commands/__pycache__/loadISO3166.cpython-34.pyc
iprir/management/commands/__pycache__/loadTLD.cpython-34.pyc
iprir/management/commands/__pycache__/loadregistry.cpython-34.pyc
iprir/management/commands/__pycache__/loadregistry.cpython-35.pyc
iprir/templates/iprir/registry.html
iprir/templates/iprir/tld.html