Metadata-Version: 1.1
Name: django-iprir
Version: 1.2.2
Summary: Retrieve, store and query information about Regional Internet Registries
Home-page: http://www.mambo5.com/
Author: Erwin van Meggelen
Author-email: erwin@mambo5.com
License: GNU General Public License
Platform: UNKNOWN
Classifier: Environment :: Web Environment
Classifier: Framework :: Django
Classifier: Intended Audience :: Developers
Classifier: License :: OSI Approved :: GNU General Public License v3 or later (GPLv3+)
Classifier: Operating System :: OS Independent
Classifier: Programming Language :: Python
Classifier: Programming Language :: Python :: 3
Classifier: Programming Language :: Python :: 3.6
Classifier: Topic :: Internet :: WWW/HTTP
Classifier: Topic :: Internet :: WWW/HTTP :: Dynamic Content
